serialroomba/__init__.py
serialroomba/controllers/__init__.py
serialroomba/controllers/cleaning.py
serialroomba/controllers/controller.py
serialroomba/controllers/environment.py
serialroomba/controllers/mode.py
serialroomba/controllers/models/__init__.py
serialroomba/controllers/models/command.py
serialroomba/controllers/models/sensor.py
serialroomba/controllers/models/state.py
serialroomba/controllers/models/validator_enum.py
serialroomba/controllers/movement.py
serialroomba/controllers/power.py
serialroomba/controllers/serial.py
serialroomba/exceptions.py
serialroomba/serialroomba.py
serialroomba-0.1.2.dist-info/COPYING
serialroomba-0.1.2.dist-info/METADATA
serialroomba-0.1.2.dist-info/WHEEL
serialroomba-0.1.2.dist-info/RECORD
