Metadata-Version: 2.1
Name: serialroomba
Version: 0.1.2
Summary: Serialroomba is a package that aims to simplify the control of a Roomba over its serial port.
Home-page: https://github.com/jtommi/serialroomba
License: GPL-3.0-or-later
Author: Thomas
Author-email: johanns.thomas@gmail.com
Requires-Python: >=3.10,<4.0
Classifier: License :: OSI Approved :: GNU General Public License v3 or later (GPLv3+)
Classifier: Programming Language :: Python :: 3
Classifier: Programming Language :: Python :: 3.10
Classifier: Programming Language :: Python :: 3.11
Requires-Dist: pyserial (>=3.5,<4.0)
Project-URL: Documentation, https://github.com/jtommi/serialroomba/blob/main/README.md
Project-URL: Repository, https://github.com/jtommi/serialroomba
